{"data":{"airtable":{"data":{"Person_Lookup":"Dorcas.2810","Dictionary_Text":"<p>a female antelope, or gazelle, a pious Christian widow at Joppa whom Peter restored to life ( <a href=\"/passage/?q=Acts+9:36-41\" target=\"_blank\" url=\"/bible/passage.aspx?q=Acts+9:36-41&amp;t=niv\">Acts 9:36-41</a> ). She was a Hellenistic Jewess, called Tabitha by the Jews and Dorcas by the Greeks.","Aliases":"Tabitha,Dorcas","Father":null,"Has_Been_to":[{"data":{"Place_Lookup":"Lydda.741","ESV_name":"Lydda"}},{"data":{"Place_Lookup":"Saron.1063","ESV_name":"Sharon"}},{"data":{"Place_Lookup":"Joppa.652","ESV_name":"Joppa"}}],"Events":[{"data":{"Event_Name":"Peter heals Aeneas and Dorcas","Start_Year":[{"data":{"Year":"41"}}]}}],"Personal_network":[{"data":{"Person_Lookup":"Peter.2745","Name":"Simon"}},{"data":{"Person_Lookup":"Aeneas.106","Name":"Aeneas"}},{"data":{"Person_Lookup":"Simon.2753","Name":"Simon"}}],"Member_of_Groups":null,"Verses":[{"data":{"Verse_Num":"36","Book":[{"data":{"Canonical_Order":44,"Osis_Name":"Acts"}}],"Chapter":[{"data":{"Chapter_Lookup":"Acts.9"}}]}},{"data":{"Verse_Num":"39","Book":[{"data":{"Canonical_Order":44,"Osis_Name":"Acts"}}],"Chapter":[{"data":{"Chapter_Lookup":"Acts.9"}}]}},{"data":{"Verse_Num":"40","Book":[{"data":{"Canonical_Order":44,"Osis_Name":"Acts"}}],"Chapter":[{"data":{"Chapter_Lookup":"Acts.9"}}]}}]}}},"pageContext":{"lookup":"Dorcas.2810"}}