{"data":{"airtable":{"data":{"Person_Lookup":"Hatach.1452","Dictionary_Text":null,"Aliases":"Hatach","Father":null,"Has_Been_to":null,"Events":null,"Personal_network":null,"Member_of_Groups":null,"Verses":[{"data":{"Verse_Num":"5","Book":[{"data":{"Canonical_Order":17,"Osis_Name":"Esth"}}],"Chapter":[{"data":{"Chapter_Lookup":"Esther.4"}}]}},{"data":{"Verse_Num":"6","Book":[{"data":{"Canonical_Order":17,"Osis_Name":"Esth"}}],"Chapter":[{"data":{"Chapter_Lookup":"Esther.4"}}]}},{"data":{"Verse_Num":"9","Book":[{"data":{"Canonical_Order":17,"Osis_Name":"Esth"}}],"Chapter":[{"data":{"Chapter_Lookup":"Esther.4"}}]}},{"data":{"Verse_Num":"10","Book":[{"data":{"Canonical_Order":17,"Osis_Name":"Esth"}}],"Chapter":[{"data":{"Chapter_Lookup":"Esther.4"}}]}}]}}},"pageContext":{"lookup":"Hatach.1452"}}