{"data":{"airtable":{"data":{"Person_Lookup":"Ezra.1245","Dictionary_Text":null,"Aliases":"Ezra","Father":[{"data":{"Person_Lookup":"Seraiah.2494","Name":"Seraiah"}}],"Has_Been_to":null,"Events":null,"Personal_network":null,"Member_of_Groups":[{"data":{"Group_Name":"Tribe of Levi"}}],"Verses":[{"data":{"Verse_Num":"1","Book":[{"data":{"Canonical_Order":15,"Osis_Name":"Ezra"}}],"Chapter":[{"data":{"Chapter_Lookup":"Ezra.7"}}]}},{"data":{"Verse_Num":"6","Book":[{"data":{"Canonical_Order":15,"Osis_Name":"Ezra"}}],"Chapter":[{"data":{"Chapter_Lookup":"Ezra.7"}}]}},{"data":{"Verse_Num":"10","Book":[{"data":{"Canonical_Order":15,"Osis_Name":"Ezra"}}],"Chapter":[{"data":{"Chapter_Lookup":"Ezra.7"}}]}},{"data":{"Verse_Num":"11","Book":[{"data":{"Canonical_Order":15,"Osis_Name":"Ezra"}}],"Chapter":[{"data":{"Chapter_Lookup":"Ezra.7"}}]}},{"data":{"Verse_Num":"12","Book":[{"data":{"Canonical_Order":15,"Osis_Name":"Ezra"}}],"Chapter":[{"data":{"Chapter_Lookup":"Ezra.7"}}]}},{"data":{"Verse_Num":"21","Book":[{"data":{"Canonical_Order":15,"Osis_Name":"Ezra"}}],"Chapter":[{"data":{"Chapter_Lookup":"Ezra.7"}}]}},{"data":{"Verse_Num":"25","Book":[{"data":{"Canonical_Order":15,"Osis_Name":"Ezra"}}],"Chapter":[{"data":{"Chapter_Lookup":"Ezra.7"}}]}},{"data":{"Verse_Num":"1","Book":[{"data":{"Canonical_Order":15,"Osis_Name":"Ezra"}}],"Chapter":[{"data":{"Chapter_Lookup":"Ezra.10"}}]}},{"data":{"Verse_Num":"2","Book":[{"data":{"Canonical_Order":15,"Osis_Name":"Ezra"}}],"Chapter":[{"data":{"Chapter_Lookup":"Ezra.10"}}]}},{"data":{"Verse_Num":"5","Book":[{"data":{"Canonical_Order":15,"Osis_Name":"Ezra"}}],"Chapter":[{"data":{"Chapter_Lookup":"Ezra.10"}}]}},{"data":{"Verse_Num":"6","Book":[{"data":{"Canonical_Order":15,"Osis_Name":"Ezra"}}],"Chapter":[{"data":{"Chapter_Lookup":"Ezra.10"}}]}},{"data":{"Verse_Num":"10","Book":[{"data":{"Canonical_Order":15,"Osis_Name":"Ezra"}}],"Chapter":[{"data":{"Chapter_Lookup":"Ezra.10"}}]}},{"data":{"Verse_Num":"16","Book":[{"data":{"Canonical_Order":15,"Osis_Name":"Ezra"}}],"Chapter":[{"data":{"Chapter_Lookup":"Ezra.10"}}]}},{"data":{"Verse_Num":"1","Book":[{"data":{"Canonical_Order":16,"Osis_Name":"Neh"}}],"Chapter":[{"data":{"Chapter_Lookup":"Nehemiah.8"}}]}},{"data":{"Verse_Num":"2","Book":[{"data":{"Canonical_Order":16,"Osis_Name":"Neh"}}],"Chapter":[{"data":{"Chapter_Lookup":"Nehemiah.8"}}]}},{"data":{"Verse_Num":"4","Book":[{"data":{"Canonical_Order":16,"Osis_Name":"Neh"}}],"Chapter":[{"data":{"Chapter_Lookup":"Nehemiah.8"}}]}},{"data":{"Verse_Num":"5","Book":[{"data":{"Canonical_Order":16,"Osis_Name":"Neh"}}],"Chapter":[{"data":{"Chapter_Lookup":"Nehemiah.8"}}]}},{"data":{"Verse_Num":"6","Book":[{"data":{"Canonical_Order":16,"Osis_Name":"Neh"}}],"Chapter":[{"data":{"Chapter_Lookup":"Nehemiah.8"}}]}},{"data":{"Verse_Num":"9","Book":[{"data":{"Canonical_Order":16,"Osis_Name":"Neh"}}],"Chapter":[{"data":{"Chapter_Lookup":"Nehemiah.8"}}]}},{"data":{"Verse_Num":"13","Book":[{"data":{"Canonical_Order":16,"Osis_Name":"Neh"}}],"Chapter":[{"data":{"Chapter_Lookup":"Nehemiah.8"}}]}},{"data":{"Verse_Num":"26","Book":[{"data":{"Canonical_Order":16,"Osis_Name":"Neh"}}],"Chapter":[{"data":{"Chapter_Lookup":"Nehemiah.12"}}]}},{"data":{"Verse_Num":"36","Book":[{"data":{"Canonical_Order":16,"Osis_Name":"Neh"}}],"Chapter":[{"data":{"Chapter_Lookup":"Nehemiah.12"}}]}}]}}},"pageContext":{"lookup":"Ezra.1245"}}