{"data":{"airtable":{"data":{"Place_Lookup":"Zion.1263","Dictionary_text":null,"Place_ID":1263,"KJV_Name":"Zion","Has_been_here":null,"Events_here":null,"Verses":["recPIKEeOdPvmwGTg","recCkvehY5FhHJHVA","recONBmX7M4VDLsPc","recyF8LfbEL71fOfK","reclYFC1axY8YkWRi","rech4EylEDVBBWZlv","recwtubOiFRT6v9ik","recunQhF7d5OUcO4y","recq6FKwdJlNTduhu","recWwh7dgWZ8Wz31X","recSQ2mwrWoUZ9g0t","recWlrzrpjb2qZJfe","reczNACXJ4aLVYEco","recRrDhkXh71tOrOi","recIOptCJjq74z6Zy","recN9pMLR4EPteHRv","recAQKmVyBn2dTdc4","recXjcklxp69jr6E7","recAJfFfkiFeAGXW2","recGkoI6FZ8TLacAk","recYF9YXdyDcNfCdb","recMnZgZf7XmiCnTm","recn60448V0pX7Fhc","recXRNOM9p2u1aNAz","recvr8BriLehFOuS1","recw4BC1ed48neSf9","recpJzxnDgkIEuubD","recqPRkZcaXltahGA","recUKAXDE9TjTX4SX","recU82G4S24yxKiwG","recKMquHJx9QHayBM","recJgSspFs5PVhUH2","recmxnceRrs36Tc0L","recVYxh59OKLNtsmg","recRmkWUqCI1XKVAh","rec4IMeQydqMSYtLJ","recNFTepu1PERdMRZ","reckJiEk4C0db15va","recfpajoInv72CQK2","rec6ukqVUyNtKDUUj","recmSdCIVUojk5U1S","recZHNaPzwjvcBxiL","recgpOIKjBJqq8W7Y","reclRHzW0ZITfcsfq","recDFpmtZIydkqx7F","rec4Gpza2WwZ8mBl4","recsBx8yKxwJS8sJx","recLou4Ifg7hNRSOV","rechXJmicvNEoE2fU","recX5MTpDe6mKuGJE","reclYkldZoVYdCjyF","recyMXrxpO9gE3wVt","rec2zj1hUxEiljgat","rechM6CWXhv3RqqmC","recl0gLlnz6B2l4Bf","recyd6BX6nS8KE1iJ","rec7Do7vsmKXQOwQ5","recq5J4AlI6U1zXm5","recIlNsB90mQDMiqa","recIMUIYlNl7dHBIl","recbTqxYWcG9StLAW","rec8TlU3bowOaHYO3","recDMsVifFfpwPjQF","recWJ75W1IdJKqdls","reclCgERWZqZGzaz3","recdZgu71OKIplFJq","rec8QYaubGNqHyfgI","recb1J48WRzU5tZRZ","recOXlCOayisOfbww","recHdUEcgXgkvZhSH","recMUfTLsiPdzsE5Y","recgWmjxkshpMIlK0","recisE28EE6ug6FF8","rec6BHvQrXfx69seQ","rectuXAFXVSMdPHns","rect0hzpVrUCyRAxb","recDJCx3QMFY3M935","recZuaPUywEA738N7","recA4GuMLsLyF8CLl","recFtQK3YRRM2tdTd","recKp4FpxNly8I0wI","recDjv3yxrGlAVXxk","recbLm0A6Wp1EIW7J","recd4MwJH9elkxsmi","recRAadtQUf0oSpjF","recK0LPbWWWjFokGG","recOQXFhPt9Hw5TGZ","recFc1Xh9PgupFiYK","rec2tJ9khuvEFIyOR","recs4AO702mxjDBdj","rec58Co4fhbwzVSzA","recdY8KiycM4R4OpV","recqeuWaBwLVsROoq","recbi3Lir6zlQKdkH","recHd6CBwVtA30RZs","reccIP02L88RMjo4w","rec1Daiao7qIl50oC","recAKyoKIf4KyaBkU","recQqeHfZ5kvnF4Dh","recEN0PjA3BYFkNGY","recD5xZ40I6w9d1WL","recomL7NBZ6CxgG3z","recn1JJFBtJtTVUII","recTwwqhWIWrkCuhe","reckFqTAVfIpMsOfF","recld9Jmq3ghfJcBm","recRAuQEAuROp8jwm","recizmEUhYhAxRTRg","recOEh7QXTY74Yi6A","recgZbH7pyzOzinHI","recUs2zRXLcYVyvcl","rec335CGItTG1SVe9","recgeNFwzJlS9ZSc5","recHZLqNAsQoVB8NH","recI5dVLqpuknJv7S","recYMFsaMwE5DPEZ9","recu7Pui9Cm0Xfz2O","rechQyblrHLYpekc2","recfoAEFs1Tp1OcaC","reccET0n6OE7PrZqp","reckEV717vU1e1WmP","recgDPVtY9EW12YcN","rec9lXYi0fb0Vv42N","recGyMzEmZXA7wOAt","rec2WQDF4cyCf1rbr","recvHwzwHsr5E1BlF","recArldbJLz8tnMGn","reccC4g8RsaW8Hhtj","recAWWlP9zjuNtsdp","recuvMnct6mTViz1r","recfjaTgQD8sXoKgj","rec8Wv0lis7W21pIt","rec79qhkF37N3Bi61","recAHnVWqjDCWDKIX","recaHkFfMdnQ7tY2A","recGQseyJEumqCrOz","recTyzrQOeFjgAhJk","recBjAlRfESLc989k","rec2Ise0K1wcXeQP6"]}}},"pageContext":{"lookup":"Zion.1263"}}