{"data":{"airtable":{"data":{"Place_Lookup":"Beersheba.170","Dictionary_text":null,"Recogito_Type":"settlement","Place_ID":170,"KJV_Name":"Beersheba","Has_been_here":null,"Events_here":null,"Verses":["recfKtvnh1pMy4i3u","recLJi1eV4YwEv1fC","recB9Udl7ALwB5o0U","recWLRpKILWSL7aIA","recNSd9dKWzNNr3Om","recftCmriomIvLFN6","recyCHNla6LI7Ob4x","rec5Yse1GBBsmXXkp","recaDA8ZgBrTdG4KR","recpjjHn8uwSDAAEY","rec9vH4Ym6JZGespX","recCRPTx3QEUbEDnD","rec0OmkBbUlr2gWCL","recU6enfUaYQixfI4","recJMs8atgX4chBgd","recY1UPKSc7cxu5FO","rechg9Olq3XhGkNMD","rec4OmmYpV8YN25FI","recVWuDxPdatFQzIm","recqvAGf8BJ9fpAG7","recf6yA5NsjSWmQiF","recUsCeqzuv4fAeRS","recHWGmhNc4w7XVem","recNfS4AshZ1dA3Ak","rec7ZnSch97dIVZFo","recvyCnLOdVCoTEDQ","rechkvccrb2PZ3zwc","recoPR38le9wXjvuo","recVNdLEFtmp1zdDP","recgfxFvyvq2RKWiI","recvXO7FzZSNA0h8q","recTG6GHSUOfRtC8D"]}}},"pageContext":{"lookup":"Beersheba.170"}}