{"data":{"airtable":{"data":{"Person_Lookup":"Sherebiah.2668","Dictionary_Text":null,"Aliases":"Sherebiah","Father":null,"Has_Been_to":null,"Events":null,"Personal_network":null,"Member_of_Groups":null,"Verses":[{"data":{"Verse_Num":"12","Book":[{"data":{"Canonical_Order":16,"Osis_Name":"Neh"}}],"Chapter":[{"data":{"Chapter_Lookup":"Nehemiah.10"}}]}},{"data":{"Verse_Num":"8","Book":[{"data":{"Canonical_Order":16,"Osis_Name":"Neh"}}],"Chapter":[{"data":{"Chapter_Lookup":"Nehemiah.12"}}]}},{"data":{"Verse_Num":"24","Book":[{"data":{"Canonical_Order":16,"Osis_Name":"Neh"}}],"Chapter":[{"data":{"Chapter_Lookup":"Nehemiah.12"}}]}}]}}},"pageContext":{"lookup":"Sherebiah.2668"}}